jet/__init__.py
jet/cli.py
jet/decoding.py
jet/engine_hf.py
jet/engine_unsloth.py
jet/eval.py
jet/logging.py
jet/merge.py
jet/metrics.py
jet/models.py
jet/train.py
jet/api/__init__.py
jet/api/app.py
jet/api/cli.py
jet/sdk/client.py
jet/sdk/training.py
jet/service/app.py
jet_ai_sdk-0.2.0.dist-info/METADATA
jet_ai_sdk-0.2.0.dist-info/WHEEL
jet_ai_sdk-0.2.0.dist-info/top_level.txt
jet_ai_sdk-0.2.0.dist-info/RECORD
