Metadata-Version: 2.4
Name: jet-ai-sdk
Version: 0.2.0
Summary: Jet: Production fine-tuning SDK with Unsloth/HF engines, vLLM serving, and REST API
Author: Jet Team
License-Expression: Apache-2.0
Requires-Python: >=3.10
Requires-Dist: transformers<4.49,>=4.42
Requires-Dist: datasets>=2.18
Requires-Dist: evaluate>=0.4.3
Requires-Dist: trl<0.13,>=0.9
Requires-Dist: peft>=0.10
Requires-Dist: unsloth>=0.9
Requires-Dist: bitsandbytes>=0.43
Requires-Dist: mlflow>=2.12
Requires-Dist: requests>=2.31
Provides-Extra: api
Requires-Dist: fastapi>=0.112; extra == "api"
Requires-Dist: uvicorn>=0.30; extra == "api"
Requires-Dist: websockets>=12.0; extra == "api"
Requires-Dist: pydantic>=2.0; extra == "api"
